testbed/cli/main.py
testbed/swarmit/__init__.py
testbed/swarmit/adapter.py
testbed/swarmit/controller.py
testbed/swarmit/protocol.py
swarmit-0.5.0.dist-info/METADATA
swarmit-0.5.0.dist-info/WHEEL
swarmit-0.5.0.dist-info/entry_points.txt
swarmit-0.5.0.dist-info/licenses/AUTHORS
swarmit-0.5.0.dist-info/licenses/LICENSE
swarmit-0.5.0.dist-info/RECORD
