Metadata-Version: 2.4
Name: swarmit
Version: 0.5.0
Summary: Run Your Own Robot Swarm Testbed.
Project-URL: Homepage, https://github.com/DotBots/swarmit
Project-URL: Bug Tracker, https://github.com/DotBots/swarmit/issues
Author-email: Alexandre Abadie <alexandre.abadie@inria.fr>
License: BSD
License-File: AUTHORS
License-File: LICENSE
Classifier: License :: OSI Approved :: BSD License
Classifier: Operating System :: MacOS
Classifier: Operating System :: Microsoft :: Windows
Classifier: Operating System :: POSIX :: Linux
Classifier: Programming Language :: Python :: 3
Requires-Python: >=3.7
Requires-Dist: click>=8.1.7
Requires-Dist: cryptography==43.0.1
Requires-Dist: marilib-pkg==0.7.1
Requires-Dist: pydotbot>=0.26.0
Requires-Dist: rich>=14.0.0
Requires-Dist: structlog>=24.4.0
Requires-Dist: tqdm>=4.66.5
